ihackernews.py
setup.py
ihackernews.egg-info/PKG-INFO
ihackernews.egg-info/SOURCES.txt
ihackernews.egg-info/dependency_links.txt
ihackernews.egg-info/requires.txt
ihackernews.egg-info/top_level.txt