Metadata-Version: 1.0
Name: ihackernews
Version: 1.0.0
Summary: A Python library for the iHackerNews API.
Home-page: https://github.com/dmpayton/python-ihackernews
Author: Derek Payton
Author-email: derek.payton@gmail.com
License: MIT
Platform: UNKNOWN
Classifier: Development Status :: 4 - Beta
Classifier: Intended Audience :: Developers
Classifier: License :: OSI Approved :: MIT License
Classifier: Natural Language :: English
Classifier: Programming Language :: Python
